trading_bots/__init__.py
trading_bots/__main__.py
trading_bots/bots/__init__.py
trading_bots/bots/base.py
trading_bots/bots/logging.py
trading_bots/bots/registry.py
trading_bots/bots/tasks.py
trading_bots/conf/__init__.py
trading_bots/conf/bot_template/snake_case_bot_name/__init__.py.jinja2
trading_bots/conf/bot_template/snake_case_bot_name/bot.py.jinja2
trading_bots/conf/bot_template/snake_case_bot_name/configs/default.yml
trading_bots/conf/defaults.py
trading_bots/conf/global_settings.py
trading_bots/conf/project_template/bots.py.jinja2
trading_bots/conf/project_template/secrets.yml
trading_bots/conf/project_template/settings.yml
trading_bots/conf/project_template/snake_case_project_name/__init__.py.jinja2
trading_bots/contrib/__init__.py
trading_bots/contrib/clients.py
trading_bots/contrib/converters/__init__.py
trading_bots/contrib/converters/base.py
trading_bots/contrib/converters/bitcoin_average.py
trading_bots/contrib/converters/coinmarketcap.py
trading_bots/contrib/converters/currencylayer.py
trading_bots/contrib/converters/open_exchange_rates.py
trading_bots/contrib/errors.py
trading_bots/contrib/exchanges/__init__.py
trading_bots/contrib/exchanges/base.py
trading_bots/contrib/exchanges/bitfinex/__init__.py
trading_bots/contrib/exchanges/bitfinex/clients.py
trading_bots/contrib/exchanges/bitstamp/__init__.py
trading_bots/contrib/exchanges/bitstamp/clients.py
trading_bots/contrib/exchanges/buda/__init__.py
trading_bots/contrib/exchanges/buda/clients.py
trading_bots/contrib/exchanges/kraken/__init__.py
trading_bots/contrib/exchanges/kraken/clients.py
trading_bots/contrib/models.py
trading_bots/contrib/money.py
trading_bots/contrib/utils.py
trading_bots/core/__init__.py
trading_bots/core/exceptions.py
trading_bots/core/logging.py
trading_bots/core/management/__init__.py
trading_bots/core/management/templates.py
trading_bots/core/storage.py
trading_bots/core/utils.py
trading_bots/utils.py
trading_bots-0.5.3.dist-info/entry_points.txt
trading_bots-0.5.3.dist-info/LICENSE
trading_bots-0.5.3.dist-info/WHEEL
trading_bots-0.5.3.dist-info/METADATA
trading_bots-0.5.3.dist-info/RECORD
