Metadata-Version: 2.1
Name: trading-bots
Version: 0.5.3
Summary: A simple framework for bootstrapping your Crypto Trading Bots
Home-page: https://github.com/snake575/trading-bots
License: MIT
Author: Sebastian Aranguiz
Author-email: sarang575@gmail.com
Requires-Python: >=3.6,<4.0
Classifier: Development Status :: 4 - Beta
Classifier: Environment :: Console
Classifier: Intended Audience :: Developers
Classifier: License :: OSI Approved :: MIT License
Classifier: Natural Language :: English
Classifier: Operating System :: OS Independent
Classifier: Programming Language :: Python
Classifier: Programming Language :: Python :: 3
Classifier: Programming Language :: Python :: 3 :: Only
Classifier: Programming Language :: Python :: 3.6
Classifier: Programming Language :: Python :: 3.7
Classifier: Programming Language :: Python :: 3.8
Classifier: Programming Language :: Python :: Implementation :: CPython
Classifier: Programming Language :: Python :: Implementation :: PyPy
Requires-Dist: cached-property (>=1.5.1,<2.0.0)
Requires-Dist: click (>=7.1.2,<8.0.0)
Requires-Dist: importlib_metadata (>=1.7.0,<2.0.0); python_version < "3.8"
Requires-Dist: jinja2 (>=2.11.2,<3.0.0)
Requires-Dist: maya (>=0.6.1,<0.7.0)
Requires-Dist: pygogo (>=0.12.0,<0.13.0)
Requires-Dist: pyyaml (>=5.3.1,<6.0.0)
Requires-Dist: requests (>=2.24.0,<3.0.0)
Requires-Dist: simple-settings (>=0.19.1,<0.20.0)
Requires-Dist: stringcase (>=1.2.0,<2.0.0)
Requires-Dist: trading-api-wrappers (>=0.16.10,<0.17.0)
Project-URL: Repository, https://github.com/snake575/trading-bots
